rawprasslib/__init__.py
rawprasslib/rawprasslib.py
rawprasslib-0.0.13.dist-info/LICENSE
rawprasslib-0.0.13.dist-info/METADATA
rawprasslib-0.0.13.dist-info/WHEEL
rawprasslib-0.0.13.dist-info/top_level.txt
rawprasslib-0.0.13.dist-info/RECORD
